_spookyhash.cp313-win32.pyd
spookyhash.py
spookyhash-2.1.1.dist-info/licenses/LICENSE
spookyhash-2.1.1.dist-info/METADATA
spookyhash-2.1.1.dist-info/WHEEL
spookyhash-2.1.1.dist-info/top_level.txt
spookyhash-2.1.1.dist-info/RECORD
