Metadata-Version: 2.4
Name: spookyhash
Version: 2.1.1
Summary: A Python wrapper for SpookyHash version 2
Author-email: Alen Buhanec <alen.buhanec@gmail.com>
License: MIT
Project-URL: Homepage, https://github.com/buhanec/spookyhash
Project-URL: Repository, https://github.com/buhanec/spookyhash
Project-URL: Issues, https://github.com/buhanec/spookyhash/issues
Keywords: SpookyHash,hashlib
Classifier: Topic :: Software Development :: Libraries
Classifier: Development Status :: 5 - Production/Stable
Classifier: Programming Language :: Python :: 3
Classifier: Programming Language :: Python :: 3.7
Classifier: Programming Language :: Python :: 3.8
Classifier: Programming Language :: Python :: 3.9
Classifier: Programming Language :: Python :: 3.10
Classifier: Programming Language :: Python :: 3.11
Classifier: Programming Language :: Python :: 3.12
Classifier: Programming Language :: Python :: 3.13
Classifier: Programming Language :: Python :: 3.14
Classifier: License :: OSI Approved :: MIT License
Classifier: Operating System :: OS Independent
Classifier: Typing :: Typed
License-File: LICENSE
Provides-Extra: test
Requires-Dist: pytest; extra == "test"
Requires-Dist: hypothesis; extra == "test"
Dynamic: license-file
